{"format":1,"files":{"forms_py":{"hash":"3fb9044c56947abb3da866f3b4e487cd","index":{"nums":[1,17,0,0,0,0,0],"html_filename":"forms_py.html","relative_filename":"forms.py"}},"config_py":{"hash":"c4eb2d760109edd8c82b8c39c25fdfc3","index":{"nums":[1,8,0,0,0,0,0],"html_filename":"config_py.html","relative_filename":"config.py"}},"views_py":{"hash":"2f7a74b8c66379197e9592028135819f","index":{"nums":[1,88,0,8,0,0,0],"relative_filename":"views.py","html_filename":"views_py.html"}},"models_py":{"hash":"5f7301dc58e83b2b7a4b93130149c714","index":{"nums":[1,33,0,2,0,0,0],"html_filename":"models_py.html","relative_filename":"models.py"}},"test_py":{"hash":"811351214aea5b79af721dddf7597092","index":{"nums":[1,121,0,0,0,0,0],"html_filename":"test_py.html","relative_filename":"test.py"}}},"version":"4.3.4","settings":"dc8d15ada52b0fe0cbd84c86e8cb9bdb"}